q2_omxware/__init__.py
q2_omxware/_omxware.py
q2_omxware/_util.py
q2_omxware/_version.py
q2_omxware/plugin_setup.py
q2_omxware-1.0.0.dist-info/LICENSE
q2_omxware-1.0.0.dist-info/METADATA
q2_omxware-1.0.0.dist-info/WHEEL
q2_omxware-1.0.0.dist-info/entry_points.txt
q2_omxware-1.0.0.dist-info/top_level.txt
q2_omxware-1.0.0.dist-info/RECORD
